{"assets/Order.mp3":["assets/Order.mp3"],"assets/Siren.mp3":["assets/Siren.mp3"],"assets/images/Assign.png":["assets/images/Assign.png"],"assets/images/Cancell.png":["assets/images/Cancell.png"],"assets/images/Completed.png":["assets/images/Completed.png"],"assets/images/Dailycuts.png":["assets/images/Dailycuts.png"],"assets/images/New Order.png":["assets/images/New Order.png"],"assets/images/Re-Assign.png":["assets/images/Re-Assign.png"],"assets/images/loading.gif":["assets/images/loading.gif"],"assets/images/logo 1.png":["assets/images/logo 1.png"],"assets/images/logo.png":["assets/images/logo.png"],"assets/images/medicines.jpg":["assets/images/medicines.jpg"],"assets/images/no-order.png":["assets/images/no-order.png"],"assets/images/no-products-found.png":["assets/images/no-products-found.png"],"assets/images/noimage.png":["assets/images/noimage.png"],"assets/images/otp.png":["assets/images/otp.png"],"packages/cupertino_icons/assets/CupertinoIcons.ttf":["packages/cupertino_icons/assets/CupertinoIcons.ttf"]}